appwrite_lab/__init__.py
appwrite_lab/_orchestrator.py
appwrite_lab/_state.py
appwrite_lab/config.py
appwrite_lab/labs.py
appwrite_lab/models.py
appwrite_lab/utils.py
appwrite_lab/automations/__init__.py
appwrite_lab/automations/automations.py
appwrite_lab/automations/common.py
appwrite_lab/automations/functions.py
appwrite_lab/automations/models.py
appwrite_lab/automations/utils.py
appwrite_lab/automations/scripts/__init__.py
appwrite_lab/automations/scripts/create_api_key.py
appwrite_lab/automations/scripts/create_project.py
appwrite_lab/automations/scripts/create_user_and_api_key.py
appwrite_lab/automations/scripts/sync_project.py
appwrite_lab/cli/entry.py
appwrite_lab/cli/list_menu.py
appwrite_lab/cli/new_menu.py
appwrite_lab/cli/stop_menu.py
appwrite_lab/cli/sync_menu.py
appwrite_lab/templates/docker_compose_1_7_4.yml
appwrite_lab/templates/environment/dotenv
appwrite_lab/templates/extras/mailpit/docker_compose.yml
appwrite_lab/templates/extras/twilio-shim/docker_compose.yml
appwrite_lab/templates/playwright/docker_compose.yml
appwrite_lab/test_suite/__init__.py
appwrite_lab/test_suite/fixtures.py
appwrite_lab/tools/__init__.py
appwrite_lab/tools/sms.py
appwrite_lab-0.1.5.dist-info/licenses/LICENSE
scripts/selinuxify_template_patch.py
tests/conftest.py
tests/test_labs.py
tests/test_orchestrator.py
tests/test_tools.py
twilio-shim/main.py
appwrite_lab-0.1.5.dist-info/METADATA
appwrite_lab-0.1.5.dist-info/WHEEL
appwrite_lab-0.1.5.dist-info/entry_points.txt
appwrite_lab-0.1.5.dist-info/top_level.txt
appwrite_lab-0.1.5.dist-info/RECORD
