Metadata-Version: 2.4
Name: appwrite-lab
Version: 0.1.5
Summary: Zero-click Appwrite test environments.
License-Expression: MIT
Requires-Python: >=3.11
License-File: LICENSE
Requires-Dist: playwright
Requires-Dist: typer>=0.16.0
Requires-Dist: python-dotenv>=1.1.0
Requires-Dist: pytest>=8.4.1
Requires-Dist: httpx>=0.28.1
Requires-Dist: pytest-asyncio>=1.1.0
Dynamic: license-file
